utilsapi/__init__.py
utilsapi/api.py
utilsapi/static/__init__.py
utilsapi/static/funcs.py
utilsapi/static/values.py
utilsapi-2.dist-info/METADATA
utilsapi-2.dist-info/WHEEL
utilsapi-2.dist-info/top_level.txt
utilsapi-2.dist-info/RECORD
