Metadata-Version: 2.1
Name: utilsapi
Version: 2
Summary: Test Pack
Home-page: UNKNOWN
Author: Capo Loup
Author-email: <loupcapo4@gmail.com>
License: UNKNOWN
Keywords: python,first package
Platform: UNKNOWN
Classifier: Development Status :: 3 - Alpha
Classifier: Intended Audience :: Education
Classifier: Programming Language :: Python :: 2
Classifier: Programming Language :: Python :: 3
Classifier: Operating System :: MacOS :: MacOS X
Classifier: Operating System :: Microsoft :: Windows
